quantum_kite.libs/libgomp-a34b3233.so.1.0.0
kite/configuration.py
kite/disorder.py
kite/execute.py
kite/system.py
kite/calculation.py
kite/modification.py
kite/__init__.py
kite/lib/libhdf5.so
kite/lib/libhdf5.so.310
kite/lib/libhdf5_cpp.so.310
kite/lib/kitecore.cpython-312-x86_64-linux-gnu.so
kite/lib/COPYING
kite/lib/libhdf5_cpp.so
kite/lib/libhdf5.so.310.2.0
kite/lib/libhdf5_cpp.so.310.0.2
kite/lib/__init__.py
kite/tests/test_ldos.py
kite/tests/test_arpes.py
kite/tests/lattices.py
kite/tests/test_conductivity.py
kite/tests/conftest.py
kite/tests/test_dos.py
kite/tests/test_guassianwavepacket.py
kite/tests/local.cfg
kite/tests/__init__.py
kite/tests/baseline_data/guassianwavepacket/guassianwavepacket[square-gwp].pbz
kite/tests/baseline_data/ldos/ldos[8-square-ldos].pbz
kite/tests/baseline_data/ldos/structuraldisorder[11-graphene-structuraldisorder].pbz
kite/tests/baseline_data/conductivity/dc[9-square-dc].pbz
kite/tests/baseline_data/conductivity/optical[5-graphene-optcond].pbz
kite/tests/baseline_data/conductivity/opticalnonlinear[6-graphene-optnonl].pbz
kite/tests/baseline_data/dos/dos[3-haldane-dos].pbz
kite/tests/baseline_data/dos/dos[4-cubic-dos].pbz
kite/tests/baseline_data/dos/dos[square-large].pbz
kite/tests/baseline_data/dos/mag[cube-mag3d].pbz
kite/tests/baseline_data/dos/mag[square-mag2d].pbz
kite/tests/baseline_data/dos/dos[0-square-speed].pbz
kite/tests/baseline_data/dos/dos[1-square-dos].pbz
kite/tests/baseline_data/dos/dos[2-graphene-dos].pbz
kite/tests/baseline_data/arpes/arpes[square-arpes].pbz
kite/tests/baseline_data/arpes/arpes[10-square-arpes].pbz
kite/examples/dos_square_lattice.py
kite/examples/dos_cubic_lattice_twisted_bc.py
kite/examples/ldos_graphene.py
kite/examples/arpes_cubic.py
kite/examples/dos_twisted_bilayer.py
kite/examples/dos_fu_kane_mele_model.py
kite/examples/dos_vacancies.py
kite/examples/dos_optcond_gaussian_disorder.py
kite/examples/hbn_optcond2_vacancies.py
quantum_kite-0.0.4.dist-info/WHEEL
quantum_kite-0.0.4.dist-info/LICENSE.md
quantum_kite-0.0.4.dist-info/top_level.txt
quantum_kite-0.0.4.dist-info/RECORD
quantum_kite-0.0.4.dist-info/METADATA
