Metadata-Version: 2.1
Name: quantum-kite
Version: 0.0.4
Summary: KITE: Real-space quantum transport simulator. (c) 2018-2023, Quantum-Kite team
Author: Simão M. João, João M.V.P Lopes, Tatiana G. Rappoport, Misa Andelkovic, Lucian Covaci, Aires Ferreira, João P.S. Pires, Bert Jorissen, Emile Aerts, Robin Smeyers
Maintainer-email: Bert Jorissen <info@bertjorissen.be>
License: 
Project-URL: repository, https://github.com/quantum-kite/kite
Project-URL: homepage, https://quantum-kite.com/
Project-URL: documentation, https://quantum-kite.com/
Project-URL: changelog, https://github.com/quantum-kite/kite/blob/master/changelog.md
Keywords: pybinding,tight-binding,solid-state physics,physics,cmt,quantum,transport,graphene,TMD,KPM,CPGF
Classifier: Development Status :: 5 - Production/Stable
Classifier: Intended Audience :: Science/Research
Classifier: Topic :: Scientific/Engineering :: Physics
Classifier: License :: OSI Approved :: BSD License
Classifier: Programming Language :: C++
Classifier: Programming Language :: Python :: 3 :: Only
Classifier: Programming Language :: Python :: 3.9
Classifier: Programming Language :: Python :: 3.10
Classifier: Programming Language :: Python :: 3.11
Classifier: Programming Language :: Python :: 3.12
Classifier: Programming Language :: Python :: Implementation :: CPython
Requires-Python: >=3.9
License-File: LICENSE.md
Requires-Dist: h5py ==3.11.0
Requires-Dist: pybinding-dev >=0.9.5
